django_oss_storage/__init__.py
django_oss_storage/backends.py
django_oss_storage/defaults.py
django5_oss-1.1.1.dist-info/LICENSE
django5_oss-1.1.1.dist-info/METADATA
django5_oss-1.1.1.dist-info/WHEEL
django5_oss-1.1.1.dist-info/top_level.txt
django5_oss-1.1.1.dist-info/RECORD
